bib_lookup/__init__.py
bib_lookup/_bib.py
bib_lookup/_const.py
bib_lookup/bib_lookup.py
bib_lookup/citation_mixin.py
bib_lookup/cli.py
bib_lookup/utils.py
bib_lookup/version.py
bib_lookup-0.1.2.dist-info/METADATA
bib_lookup-0.1.2.dist-info/WHEEL
bib_lookup-0.1.2.dist-info/entry_points.txt
bib_lookup-0.1.2.dist-info/licenses/LICENSE
bib_lookup-0.1.2.dist-info/RECORD
