Metadata-Version: 2.4
Name: bib-lookup
Version: 0.1.2
Summary: A useful tool for looking up Bib entries using DOI, or pubmed ID (or URL), or arXiv ID (or URL).
Project-URL: Homepage, https://github.com/DeepPSP/bib_lookup
Author-email: DeepPSP <wenh06@gmail.com>
License: MIT License
License-File: LICENSE
Classifier: License :: OSI Approved :: MIT License
Classifier: Operating System :: OS Independent
Classifier: Programming Language :: Python
Classifier: Programming Language :: Python :: 3
Classifier: Programming Language :: Python :: 3.9
Classifier: Programming Language :: Python :: 3.10
Classifier: Programming Language :: Python :: 3.11
Classifier: Programming Language :: Python :: 3.12
Classifier: Programming Language :: Python :: 3.13
Classifier: Programming Language :: Python :: 3.14
Requires-Python: >=3.9
Requires-Dist: beautifulsoup4
Requires-Dist: feedparser
Requires-Dist: numpy
Requires-Dist: packaging
Requires-Dist: pandas
Requires-Dist: pyyaml
Requires-Dist: requests
Provides-Extra: app
Requires-Dist: streamlit; extra == 'app'
Provides-Extra: dev
Requires-Dist: ipython; extra == 'dev'
Requires-Dist: pre-commit; extra == 'dev'
Requires-Dist: pytest; extra == 'dev'
Requires-Dist: pytest-cov; extra == 'dev'
Requires-Dist: pytest-xdist; extra == 'dev'
Requires-Dist: streamlit; extra == 'dev'
Provides-Extra: test
Requires-Dist: ipython; extra == 'test'
Requires-Dist: pre-commit; extra == 'test'
Requires-Dist: pytest; extra == 'test'
Requires-Dist: pytest-cov; extra == 'test'
Requires-Dist: pytest-xdist; extra == 'test'
